{"canvas":{"props":{"storedElements":["9299c737701d4f2d9b8e5917961b9df1","00f6e1f5325043b7982e674e9edfc136","a9a56a32df544845abb326e1a9ae53f1","d6a77009f05c4f1993c5f8fa09f877e6","c1f4bd3a9f15410bb1b456498714c801","b6021a66fb2846c6b2ac6199b6d05f04","dcbc4c16710e406bb8aa51212f16e652","7ba0b830051c44c2a747b32112f6bfea","92fc317f81f247a39f1cc3ec303a2b57","65df6752972c4518abcdacbfe099f957","75fd90c91a954931ab20b6ee63e687ed"]},"type":"Canvas","v":"2.1"},"8f5bf8975d210ebd3bfda422c89e5496":{"props":{"codeComponentId":"107ca6ad-4bec-58b1-bad1-6df013ae36a8","codeComponentPresetId":"2105e165-8e08-54f6-8de8-1134ed759126","framework":"react","revisionId":"11ae5085-14b5-4903-82cd-205de471600d_88c388d11fea202a76bac3ad8f99bacfb4fddf9b","x":200,"y":50},"type":"CodeComponent"},"91be6d773e2b4fb3a6c2b8b735ae091e":{"props":{"name":"AppBar","keepRatio":false,"x":0,"y":0,"opacity":100,"anchorX":0,"anchorY":0,"locked":0,"stateIa":"visible","fixed":0,"elementBlur":0,"mixBlendMode":"normal","constraints":{"auto":true,"x":{"type":"stretch"},"y":{"type":"stretch"}},"sketchReadOnly":0,"flipHorizontal":false,"flipVertical":false,"layerColor":"","hasClippingMask":false,"customStyles":[],"codeComponentId":"31a0ce1a-5ab5-5138-a2b8-4e4260e115df","codeComponentPresetId":"7aaf72b8-1ed9-5191-8803-e075983f2d28","desiredHeight":100,"desiredWidth":1440,"framework":"react","libraryId":-1,"revisionId":"11ae5085-14b5-4903-82cd-205de471600d_88c388d11fea202a76bac3ad8f99bacfb4fddf9b"},"type":"CodeComponent","v":"2.1"},"ac56ef8a76154b078f8c47e5220040f3":{"props":{"name":"AppBar","keepRatio":false,"x":0,"y":0,"opacity":100,"anchorX":0,"anchorY":0,"locked":0,"stateIa":"visible","fixed":0,"elementBlur":0,"mixBlendMode":"normal","constraints":{"auto":true,"x":{"type":"stretch"},"y":{"type":"stretch"}},"sketchReadOnly":0,"flipHorizontal":false,"flipVertical":false,"layerColor":"","hasClippingMask":false,"customStyles":[],"codeComponentId":"31a0ce1a-5ab5-5138-a2b8-4e4260e115df","codeComponentPresetId":"7aaf72b8-1ed9-5191-8803-e075983f2d28","desiredHeight":100,"desiredWidth":1440,"framework":"react","libraryId":-1,"revisionId":"11ae5085-14b5-4903-82cd-205de471600d_88c388d11fea202a76bac3ad8f99bacfb4fddf9b"},"type":"CodeComponent","v":"2.1"},"3518107432e04ef7a82251b7475c7263":{"props":{"name":"AppBar","keepRatio":false,"x":86,"y":77,"opacity":100,"anchorX":0,"anchorY":0,"locked":0,"stateIa":"visible","fixed":0,"elementBlur":0,"mixBlendMode":"normal","constraints":{"auto":true,"x":{"type":"stretch"},"y":{"type":"stretch"}},"sketchReadOnly":0,"flipHorizontal":false,"flipVertical":false,"layerColor":"","hasClippingMask":false,"customStyles":[],"codeComponentId":"31a0ce1a-5ab5-5138-a2b8-4e4260e115df","codeComponentPresetId":"7aaf72b8-1ed9-5191-8803-e075983f2d28","desiredHeight":100,"desiredWidth":300,"framework":"react","libraryId":-1,"revisionId":"11ae5085-14b5-4903-82cd-205de471600d_88c388d11fea202a76bac3ad8f99bacfb4fddf9b"},"type":"CodeComponent","v":"2.1"},"c2630ccab8654b2fb990df98f28f2d4e":{"props":{"name":"AppBar","keepRatio":false,"x":113,"y":127,"opacity":100,"anchorX":0,"anchorY":0,"locked":0,"stateIa":"visible","fixed":0,"elementBlur":0,"mixBlendMode":"normal","constraints":{"auto":true,"x":{"type":"stretch"},"y":{"type":"stretch"}},"sketchReadOnly":0,"flipHorizontal":false,"flipVertical":false,"layerColor":"","hasClippingMask":false,"customStyles":[],"codeComponentId":"31a0ce1a-5ab5-5138-a2b8-4e4260e115df","codeComponentPresetId":"7aaf72b8-1ed9-5191-8803-e075983f2d28","desiredHeight":100,"desiredWidth":300,"framework":"react","libraryId":-1,"revisionId":"11ae5085-14b5-4903-82cd-205de471600d_88c388d11fea202a76bac3ad8f99bacfb4fddf9b"},"type":"CodeComponent","v":"2.1"},"6e106a6a2f63437399ee10159f7df8b6":{"props":{"name":"Button","keepRatio":false,"x":267,"y":389,"opacity":100,"anchorX":0,"anchorY":0,"locked":0,"stateIa":"visible","fixed":0,"elementBlur":0,"mixBlendMode":"normal","constraints":{"auto":true,"x":{"type":"stretch"},"y":{"type":"stretch"}},"sketchReadOnly":0,"flipHorizontal":false,"flipVertical":false,"layerColor":"","hasClippingMask":false,"customStyles":[],"codeComponentId":"107ca6ad-4bec-58b1-bad1-6df013ae36a8","desiredHeight":100,"desiredWidth":300,"framework":"react","libraryId":-1,"revisionId":"11ae5085-14b5-4903-82cd-205de471600d_88c388d11fea202a76bac3ad8f99bacfb4fddf9b"},"type":"CodeComponent","v":"2.1"},"80c7d06368654d61ba16dd5ff82bd8c2":{"props":{"name":"LogoIcon","keepRatio":false,"x":227,"y":294,"opacity":100,"anchorX":0,"anchorY":0,"locked":0,"stateIa":"visible","fixed":0,"elementBlur":0,"mixBlendMode":"normal","constraints":{"auto":true,"x":{"type":"stretch"},"y":{"type":"stretch"}},"sketchReadOnly":0,"flipHorizontal":false,"flipVertical":false,"layerColor":"","hasClippingMask":false,"customStyles":[],"codeComponentId":"8863f4b2-4332-5b7a-b7d8-469bb3e4ebd4","desiredHeight":100,"desiredWidth":300,"framework":"react","libraryId":-1,"revisionId":"11ae5085-14b5-4903-82cd-205de471600d_88c388d11fea202a76bac3ad8f99bacfb4fddf9b"},"type":"CodeComponent","v":"2.1"},"efdb35970cd442418a6caeb32a331467":{"props":{"name":"AppBar","keepRatio":false,"x":133,"y":98,"opacity":100,"anchorX":0,"anchorY":0,"locked":0,"stateIa":"visible","fixed":0,"elementBlur":0,"mixBlendMode":"normal","constraints":{"auto":true,"x":{"type":"stretch"},"y":{"type":"stretch"}},"sketchReadOnly":0,"flipHorizontal":false,"flipVertical":false,"layerColor":"","hasClippingMask":false,"customStyles":[],"codeComponentId":"31a0ce1a-5ab5-5138-a2b8-4e4260e115df","codeComponentPresetId":"7aaf72b8-1ed9-5191-8803-e075983f2d28","desiredHeight":100,"desiredWidth":300,"framework":"react","libraryId":-1,"revisionId":"11ae5085-14b5-4903-82cd-205de471600d_88c388d11fea202a76bac3ad8f99bacfb4fddf9b"},"type":"CodeComponent","v":"2.1"},"3df878c3c3884987b2a54f9de970066f":{"props":{"name":"LogoIcon","keepRatio":false,"x":120,"y":360,"opacity":100,"anchorX":0,"anchorY":0,"locked":0,"stateIa":"visible","fixed":0,"elementBlur":0,"mixBlendMode":"normal","constraints":{"auto":true,"x":{"type":"stretch"},"y":{"type":"stretch"}},"sketchReadOnly":0,"flipHorizontal":false,"flipVertical":false,"layerColor":"","hasClippingMask":false,"customStyles":[],"codeComponentId":"8863f4b2-4332-5b7a-b7d8-469bb3e4ebd4","desiredHeight":100,"desiredWidth":300,"framework":"react","libraryId":-1,"revisionId":"11ae5085-14b5-4903-82cd-205de471600d_88c388d11fea202a76bac3ad8f99bacfb4fddf9b"},"type":"CodeComponent","v":"2.1"},"adf41e6ef3f84d0bbd0f65db805b6f10":{"props":{"name":"Bar","keepRatio":false,"x":190,"y":362,"opacity":100,"anchorX":0,"anchorY":0,"locked":0,"stateIa":"visible","fixed":0,"elementBlur":0,"mixBlendMode":"normal","constraints":{"auto":true,"x":{"type":"stretch"},"y":{"type":"stretch"}},"sketchReadOnly":0,"flipHorizontal":false,"flipVertical":false,"layerColor":"","hasClippingMask":false,"customStyles":[],"codeComponentId":"87ba0b35-922d-5b53-b534-f855a042e279","codeComponentPresetId":"a4c1fcbf-7bc3-5b27-a139-b09a34ce56e4","desiredHeight":100,"desiredWidth":300,"framework":"react","libraryId":-1,"revisionId":"11ae5085-14b5-4903-82cd-205de471600d_88c388d11fea202a76bac3ad8f99bacfb4fddf9b","codeComponentProps":{"children":[{"uxpinTargetElementType":"CodeComponent","overriddenCodeProps":{"children":[]},"presetElementId":"2"}]}},"type":"CodeComponent","v":"2.1"},"90b9bfe17e4f4e169abf5f1aafa28854":{"props":{"name":"LogoIcon","keepRatio":false,"x":69,"y":223,"opacity":100,"anchorX":0,"anchorY":0,"locked":0,"stateIa":"visible","fixed":0,"elementBlur":0,"mixBlendMode":"normal","constraints":{"auto":true,"x":{"type":"stretch"},"y":{"type":"stretch"}},"sketchReadOnly":0,"flipHorizontal":false,"flipVertical":false,"layerColor":"","hasClippingMask":false,"customStyles":[],"codeComponentId":"8863f4b2-4332-5b7a-b7d8-469bb3e4ebd4","desiredHeight":100,"desiredWidth":300,"framework":"react","libraryId":-1,"revisionId":"11ae5085-14b5-4903-82cd-205de471600d_88c388d11fea202a76bac3ad8f99bacfb4fddf9b"},"type":"CodeComponent","v":"2.1"},"00f6e1f5325043b7982e674e9edfc136":{"props":{"name":"AppBar","keepRatio":false,"x":0,"y":545,"opacity":100,"anchorX":0,"anchorY":0,"locked":0,"stateIa":"visible","fixed":0,"elementBlur":0,"mixBlendMode":"normal","constraints":{"auto":true,"x":{"type":"stretch"},"y":{"type":"stretch"}},"sketchReadOnly":0,"flipHorizontal":false,"flipVertical":false,"layerColor":"","hasClippingMask":false,"customStyles":[],"codeComponentId":"31a0ce1a-5ab5-5138-a2b8-4e4260e115df","codeComponentPresetId":"7aaf72b8-1ed9-5191-8803-e075983f2d28","desiredHeight":100,"desiredWidth":800,"framework":"react","libraryId":-1,"revisionId":"11ae5085-14b5-4903-82cd-205de471600d_88c388d11fea202a76bac3ad8f99bacfb4fddf9b","codeComponentProps":{"shadow":false,"children":[{"uxpinTargetElementType":"CodeComponent","overriddenCodeProps":{"children":[{"uxpinTargetElementType":"CodeComponent","overriddenCodeProps":{"children":[{"uxpinTargetElementType":"CodeComponent","overriddenCodeProps":{"style":{"fontWeight":"bold","margin-left":"2px","margin-right":"2px"}},"presetElementId":"3"},{"codeComponentId":"87ba0b35-922d-5b53-b534-f855a042e279","codeComponentProps":{"style":{"margin-left":"4px"}},"name":"Bar","id":"ac65fc42fd824c9ca28d3a4f45b457f0","uxpinTargetElementType":"CodeComponent"},{"uxpinTargetElementType":"CodeComponent","overriddenCodeProps":{"children":"File","style":{"fontWeight":"bold","margin-left":"2px","margin-right":"2px"}},"presetElementId":"3","id":"aea6b94dcb504c2da9a1d895b28fea61"},{"uxpinTargetElementType":"CodeComponent","overriddenCodeProps":{"children":"Edit","style":{"fontWeight":"bold","margin-left":"2px","margin-right":"2px"}},"presetElementId":"3","id":"8e0cef7f44e943e89e27095896e430fb"},{"uxpinTargetElementType":"CodeComponent","overriddenCodeProps":{"children":"History","style":{"fontWeight":"bold","margin-left":"2px","margin-right":"2px"}},"presetElementId":"3","id":"9900275088a14451b89f5c9dfea230b3"},{"uxpinTargetElementType":"CodeComponent","overriddenCodeProps":{"children":"Help\n","active":true},"presetElementId":"3","id":"80c32aa9e1bd485c9910a0989416828e"}]},"presetElementId":"2","id":"b6b82f9189e84e66bf2a55c8581c8b82"},{"uxpinTargetElementType":"CodeComponent","overriddenCodeProps":{"children":[{"uxpinTargetElementType":"CodeComponent","overriddenCodeProps":{"shadow":false,"variant":"flat","disabled":true},"presetElementId":"5"}]},"presetElementId":"2","id":"9f4a29bf0fdf4c2baa5597451fc3fbfe"}]},"presetElementId":"2"}]}},"type":"CodeComponent","v":"2.1"},"9299c737701d4f2d9b8e5917961b9df1":{"props":{"name":"Rectangle","width":800,"height":600,"keepRatio":false,"x":0,"y":0,"opacity":100,"anchorX":0,"anchorY":0,"locked":0,"stateIa":"visible","fixed":0,"elementBlur":0,"mixBlendMode":"normal","constraints":{"auto":true,"x":{"type":"stretch"},"y":{"type":"stretch"}},"sketchReadOnly":0,"flipHorizontal":false,"flipVertical":false,"layerColor":"","hasClippingMask":false,"customStyles":[],"maskMode":"alpha","activePoints":[],"backgroundImage":"","bezierPoints":{"point_15832454354493":[{"x":0,"y":0,"id":"point_15832454354497"},{"x":0,"y":0,"id":"point_15832454354498"}],"point_15832454354494":[{"x":800.0000000000005,"y":0,"id":"point_15832454354499"},{"x":800.0000000000005,"y":0,"id":"point_158324543544910"}],"point_15832454354495":[{"x":800.0000000000005,"y":600.0000000000001,"id":"point_158324543544911"},{"x":800.0000000000005,"y":600.0000000000001,"id":"point_158324543544912"}],"point_15832454354496":[{"x":0,"y":600.0000000000001,"id":"point_158324543544913"},{"x":0,"y":600.0000000000001,"id":"point_158324543544914"}]},"color":"#008080","isPathClosed":true,"offsetX":0,"offsetY":0,"points":[{"x":0,"y":0,"id":"point_15832454354493","type":"straight"},{"x":800.0000000000005,"y":0,"id":"point_15832454354494","type":"straight"},{"x":800.0000000000005,"y":600.0000000000001,"id":"point_15832454354495","type":"straight"},{"x":0,"y":600.0000000000001,"id":"point_15832454354496","type":"straight"}],"viewBox":"0 0 800 600","objectFit":"cover","isReversed":false,"radiusLock":true,"stroke":"#8c8c8c","strokeWidth":0,"svgGradientColor":""},"type":"SvgPolygon","v":"2.1"},"a9a56a32df544845abb326e1a9ae53f1":{"props":{"name":"artage_io_48159_1583246221-2c95f12fe07760df35236d029b78bb8d.png","width":48,"height":48,"keepRatio":false,"x":717,"y":435,"opacity":100,"anchorX":0,"anchorY":0,"locked":0,"stateIa":"visible","fixed":0,"elementBlur":0,"mixBlendMode":"normal","constraints":{"auto":true,"x":{"type":"stretch"},"y":{"type":"stretch"}},"sketchReadOnly":0,"flipHorizontal":false,"flipVertical":false,"layerColor":"","hasClippingMask":false,"customStyles":[],"blur":0,"borderBottomLeftRadius":0,"borderBottomRightRadius":0,"borderTopLeftRadius":0,"borderTopRightRadius":0,"brightness":0,"contrast":0,"crop":[],"exposure":0,"objectFit":"cover","objectPosition":"center center","radiusLock":true,"saturation":0,"sharpen":0,"src":"http://localhost:8877/upload/1/artage_io_48159_1583246221-2c95f12fe07760df35236d029b78bb8d.png","srcMod":"","vibrance":0,"autoNamed":true},"type":"Image","v":"2.1"},"d6a77009f05c4f1993c5f8fa09f877e6":{"props":{"name":"artage_io_48186_1583246213-8f9158d8ab477407e7d4aef24d4c21f0.png","width":48,"height":48,"keepRatio":true,"x":35,"y":114,"opacity":100,"anchorX":0,"anchorY":0,"locked":0,"stateIa":"visible","fixed":0,"elementBlur":0,"mixBlendMode":"normal","constraints":{"auto":true,"x":{"type":"stretch"},"y":{"type":"stretch"}},"sketchReadOnly":0,"flipHorizontal":false,"flipVertical":false,"layerColor":"","hasClippingMask":false,"customStyles":[],"blur":0,"borderBottomLeftRadius":0,"borderBottomRightRadius":0,"borderTopLeftRadius":0,"borderTopRightRadius":0,"brightness":0,"contrast":0,"crop":[],"exposure":0,"objectFit":"cover","objectPosition":"center center","radiusLock":true,"saturation":0,"sharpen":0,"src":"http://localhost:8877/upload/2/artage_io_48186_1583246213-8f9158d8ab477407e7d4aef24d4c21f0.png","srcMod":"","vibrance":0,"autoNamed":true},"type":"Image","v":"2.1"},"c1f4bd3a9f15410bb1b456498714c801":{"props":{"name":"artage_io_48177_1583246204-3d90fcf7dec4edd11decf9cf59bc9b7a.png","width":48,"height":48,"keepRatio":true,"x":35,"y":10,"opacity":100,"anchorX":0,"anchorY":0,"locked":0,"stateIa":"visible","fixed":0,"elementBlur":0,"mixBlendMode":"normal","constraints":{"auto":true,"x":{"type":"stretch"},"y":{"type":"stretch"}},"sketchReadOnly":0,"flipHorizontal":false,"flipVertical":false,"layerColor":"","hasClippingMask":false,"customStyles":[],"blur":0,"borderBottomLeftRadius":0,"borderBottomRightRadius":0,"borderTopLeftRadius":0,"borderTopRightRadius":0,"brightness":0,"contrast":0,"crop":[],"exposure":0,"objectFit":"cover","objectPosition":"center center","radiusLock":true,"saturation":0,"sharpen":0,"src":"http://localhost:8877/upload/4/artage_io_48177_1583246204-3d90fcf7dec4edd11decf9cf59bc9b7a.png","srcMod":"","vibrance":0,"autoNamed":true},"type":"Image","v":"2.1"},"b6021a66fb2846c6b2ac6199b6d05f04":{"props":{"name":"My computer\n","width":97,"height":18,"keepRatio":false,"x":10,"y":64,"opacity":100,"anchorX":0,"anchorY":0,"locked":0,"stateIa":"visible","fixed":0,"elementBlur":0,"mixBlendMode":"normal","constraints":{"auto":true,"x":{"type":"stretch"},"y":{"type":"stretch"}},"sketchReadOnly":0,"flipHorizontal":false,"flipVertical":false,"layerColor":"","hasClippingMask":false,"customStyles":[],"autoNamed":true,"autoHeight":true,"autoWidth":false,"content":{"ops":[{"insert":"My computer\n"}]},"textAlign":"center"},"type":"RichTextElement","v":"2.1"},"dcbc4c16710e406bb8aa51212f16e652":{"props":{"name":"Disc D:\n","width":97,"height":18,"keepRatio":false,"x":10,"y":169,"opacity":100,"anchorX":0,"anchorY":0,"locked":0,"stateIa":"visible","fixed":0,"elementBlur":0,"mixBlendMode":"normal","constraints":{"auto":true,"x":{"type":"stretch"},"y":{"type":"stretch"}},"sketchReadOnly":0,"flipHorizontal":false,"flipVertical":false,"layerColor":"","hasClippingMask":false,"customStyles":[],"autoNamed":true,"autoWidth":false,"scrollHeight":18,"color":"#ffffff","content":{"ops":[{"insert":"Disc D:\n"}]},"textAlign":"center"},"type":"RichTextElement","v":"2.1"},"65df6752972c4518abcdacbfe099f957":{"props":{"name":"artage_io_48181_1583246938-f2a3bc86226402237609d8cc51e3f9a0.png","width":48,"height":48,"keepRatio":true,"x":35,"y":219,"opacity":100,"anchorX":0,"anchorY":0,"locked":0,"stateIa":"visible","fixed":0,"elementBlur":0,"mixBlendMode":"normal","constraints":{"auto":true,"x":{"type":"stretch"},"y":{"type":"stretch"}},"sketchReadOnly":0,"flipHorizontal":false,"flipVertical":false,"layerColor":"","hasClippingMask":false,"customStyles":[],"blur":0,"borderBottomLeftRadius":0,"borderBottomRightRadius":0,"borderTopLeftRadius":0,"borderTopRightRadius":0,"brightness":0,"contrast":0,"crop":[],"exposure":0,"objectFit":"cover","objectPosition":"center center","radiusLock":true,"saturation":0,"sharpen":0,"src":"http://localhost:8877/upload/5/artage_io_48181_1583246938-f2a3bc86226402237609d8cc51e3f9a0.png","srcMod":"","vibrance":0,"autoNamed":true},"type":"Image","v":"2.1"},"7ba0b830051c44c2a747b32112f6bfea":{"props":{"name":"Local Network\n","width":97,"height":36,"keepRatio":false,"x":10,"y":276,"opacity":100,"anchorX":0,"anchorY":0,"locked":0,"stateIa":"visible","fixed":0,"elementBlur":0,"mixBlendMode":"normal","constraints":{"auto":true,"x":{"type":"stretch"},"y":{"type":"stretch"}},"sketchReadOnly":0,"flipHorizontal":false,"flipVertical":false,"layerColor":"","hasClippingMask":false,"customStyles":[],"autoNamed":true,"autoWidth":false,"scrollHeight":18,"color":"#ffffff","content":{"ops":[{"insert":"Local Network\n"}]},"textAlign":"center"},"type":"RichTextElement","v":"2.1"},"92fc317f81f247a39f1cc3ec303a2b57":{"props":{"name":"Recycle Bin\n","width":97,"height":18,"keepRatio":false,"x":692,"y":489,"opacity":100,"anchorX":0,"anchorY":0,"locked":0,"stateIa":"visible","fixed":0,"elementBlur":0,"mixBlendMode":"normal","constraints":{"auto":true,"x":{"type":"stretch"},"y":{"type":"stretch"}},"sketchReadOnly":0,"flipHorizontal":false,"flipVertical":false,"layerColor":"","hasClippingMask":false,"customStyles":[],"autoNamed":true,"autoWidth":false,"scrollHeight":18,"color":"#ffffff","content":{"ops":[{"insert":"Recycle Bin\n"}]},"textAlign":"center"},"type":"RichTextElement","v":"2.1"},"75fd90c91a954931ab20b6ee63e687ed":{"props":{"name":"LogoIcon","keepRatio":false,"x":340,"y":700,"opacity":100,"anchorX":0,"anchorY":0,"locked":0,"stateIa":"visible","fixed":0,"elementBlur":0,"mixBlendMode":"normal","constraints":{"auto":true,"x":{"type":"stretch"},"y":{"type":"stretch"}},"sketchReadOnly":0,"flipHorizontal":false,"flipVertical":false,"layerColor":"","hasClippingMask":false,"customStyles":[],"codeComponentId":"8863f4b2-4332-5b7a-b7d8-469bb3e4ebd4","desiredHeight":100,"desiredWidth":300,"framework":"react","libraryId":-1,"revisionId":"11ae5085-14b5-4903-82cd-205de471600d_88c388d11fea202a76bac3ad8f99bacfb4fddf9b"},"type":"CodeComponent","v":"2.1"}}
